pyportfolio/__init__.py
pyportfolio/__version__.py
pyportfolio/cli.py
pyportfolio/clihelper.py
pyportfolio/constants.py
pyportfolio/mfhelper.py
pyportfolio/models.py
pyportfolio/portfolio.py
pyportfolio/scheme_factory.py
pyportfolio/scheme_filters.py
pyportfolio/scheme_utils.py
pyportfolio/transaction_filters.py
pyportfolio/transaction_utils.py
pyportfolio/utils.py
pyportfolio-1.0.1.dist-info/LICENSE
pyportfolio-1.0.1.dist-info/METADATA
pyportfolio-1.0.1.dist-info/WHEEL
pyportfolio-1.0.1.dist-info/entry_points.txt
pyportfolio-1.0.1.dist-info/top_level.txt
pyportfolio-1.0.1.dist-info/RECORD
