Metadata-Version: 2.1
Name: pyportfolio
Version: 1.0.1
Summary: CLI to consolidate and analyze your portfolio of investments
Home-page: https://github.com/kaushiksk/pyportfolio
Author: Kaushik S Kalmady
License: MIT License
Keywords: cas,portfolio
Platform: UNKNOWN
Classifier: License :: OSI Approved :: MIT License
Classifier: Programming Language :: Python :: 3.8
Classifier: Programming Language :: Python :: 3.9
Classifier: Operating System :: OS Independent
Requires-Python: >=3.8
License-File: LICENSE
Requires-Dist: requests (==2.25.1)
Requires-Dist: casparser (==0.4.8)
Requires-Dist: cutie (==0.2.2)
Requires-Dist: click (==8.0.1)
Requires-Dist: tabulate (==0.8.7)
